setup.py
DocumentedInvoices.egg-info/PKG-INFO
DocumentedInvoices.egg-info/SOURCES.txt
DocumentedInvoices.egg-info/dependency_links.txt
DocumentedInvoices.egg-info/requires.txt
DocumentedInvoices.egg-info/top_level.txt
invoicing/__init__.py
invoicing/invoice.py